api/__init__.py
api/sample.py
api/stats.py
api/tile.py
core/__init__.py
core/sample.py
core/shape.py
core/tile.py
core/types.py
picoreo-0.1.dist-info/LICENSE
picoreo-0.1.dist-info/METADATA
picoreo-0.1.dist-info/WHEEL
picoreo-0.1.dist-info/top_level.txt
picoreo-0.1.dist-info/RECORD
